[
    {
        "name" : "Programs",
        "children" : [
            {
                "name" : "7-Zip",
                "path" : "Z:/opt/apps/7-Zip/7zFM.exe"
            },
            {
                "name" : "Internet Explorer",
                "path" : "C:/windows/system32/iexplore.exe"
            },
            {
                "name" : "Notepad",
                "path" : "C:/windows/notepad.exe"
            },
            {
                "name" : "Wordpad",
                "path" : "C:/windows/system32/write.exe",
                "iconLocation" : "Z:/opt/wine/lib/wine/i386-windows/wordpad.exe"
            },
            {
                "name" : "Games",
                "children" : [
                    {
                        "name" : "WineMine",
                        "path" : "C:/windows/system32/winemine.exe"
                    }
                ]
            }
        ]
    },
    {
        "name" : "System Tools",
        "children" : [
            {
                "name" : "Test Direct3D",
                "path" : "Z:/opt/apps/TestD3D.exe"
            },
            {
                "name" : "Computer",
                "path" : "C:/windows/wfm.exe"
            },
            {
                "name" : "Task Manager",
                "path" : "C:/windows/system32/taskmgr.exe"
            },
            {
                "name" : "Registry Editor",
                "path" : "C:/windows/regedit.exe"
            },
            {
                "name" : "Command Prompt",
                "path" : "C:/windows/system32/cmd.exe"
            },
            {
                "name" : "Wine Mono Installer",
                "path" : "C:/windows/system32/control.exe",
                "cmdArgs" : "appwiz.cpl install_mono",
                "iconLocation" : "shell32.dll",
                "iconIndex" : -25
            },
            {
                "name" : "Wine Gecko Installer",
                "path" : "C:/windows/system32/control.exe",
                "cmdArgs" : "appwiz.cpl install_gecko",
                "iconLocation" : "shell32.dll",
                "iconIndex" : -25
            },
            {
                "name" : "Wine Configuration",
                "path" : "C:/windows/system32/winecfg.exe"
            }
        ]
    }
]